pytest_testdox/__init__.py
pytest_testdox/constants.py
pytest_testdox/data_structures.py
pytest_testdox/formatters.py
pytest_testdox/plugin.py
pytest_testdox/terminal.py
pytest_testdox/wrappers.py
pytest_testdox-3.1.0.dist-info/LICENSE
pytest_testdox-3.1.0.dist-info/METADATA
pytest_testdox-3.1.0.dist-info/WHEEL
pytest_testdox-3.1.0.dist-info/entry_points.txt
pytest_testdox-3.1.0.dist-info/top_level.txt
pytest_testdox-3.1.0.dist-info/RECORD
